scsketch/__init__.py
scsketch/_cli.py
scsketch/directional.py
scsketch/pbmc_161k_scsketch_setup.py
scsketch/utils.py
scsketch/static/widget.css
scsketch/static/widget.js
scsketch/widgets/__init__.py
scsketch/widgets/correlation_table.py
scsketch/widgets/divider.py
scsketch/widgets/gene_pathway_widget.py
scsketch/widgets/gene_projection_plot.py
scsketch/widgets/interactive_svg.py
scsketch/widgets/label.py
scsketch/widgets/pathway_table.py
scsketch-0.0.3.dist-info/METADATA
scsketch-0.0.3.dist-info/WHEEL
scsketch-0.0.3.dist-info/entry_points.txt
scsketch-0.0.3.dist-info/RECORD
