Metadata-Version: 2.4
Name: scsketch
Version: 0.0.3
Summary: Interactive exploration of single-cell embeddings with directional analysis
Project-URL: Homepage, https://github.com/colabobio/scsketch
Project-URL: Repository, https://github.com/colabobio/scsketch
Project-URL: Bug Tracker, https://github.com/colabobio/scsketch/issues
Author-email: Askar Temirbek <askar.temirbek@umassmed.edu>, Andres Colubri <andres.colubri@umassmed.edu>, Fritz Lekschas <code@lekschas.de>, Kris Sankaran <ksankaran@wisc.edu>
Keywords: bioinformatics,jupyter,single-cell,visualization,widget
Classifier: Development Status :: 3 - Alpha
Classifier: Intended Audience :: Science/Research
Classifier: Programming Language :: Python :: 3
Classifier: Programming Language :: Python :: 3.12
Classifier: Topic :: Scientific/Engineering :: Bio-Informatics
Classifier: Topic :: Scientific/Engineering :: Visualization
Requires-Python: >=3.12
Requires-Dist: anywidget>=0.9.0
Requires-Dist: ipywidgets>=8.0.0
Requires-Dist: jupyter-scatter>=0.21.0
Requires-Dist: llvmlite>=0.44.0
Requires-Dist: matplotlib>=3.7.0
Requires-Dist: numpy>=1.26.0
Requires-Dist: pandas>=2.0.0
Requires-Dist: requests>=2.31.0
Requires-Dist: scanpy>=1.9.0
Requires-Dist: scipy>=1.11.0
Requires-Dist: umap-learn>=0.5.7
Provides-Extra: dev
Requires-Dist: jupyterlab>=4.0.0; extra == 'dev'
Requires-Dist: llvmlite>=0.44.0; extra == 'dev'
Requires-Dist: torch>=2.2.0; extra == 'dev'
Requires-Dist: watchfiles>=0.20.0; extra == 'dev'
Provides-Extra: lab
Requires-Dist: jupyterlab>=4.0.0; extra == 'lab'
